gufo/ping/__init__.py
gufo/ping/_fast.cpython-311-x86_64-linux-musl.so
gufo/ping/_fast.pyi
gufo/ping/cli.py
gufo/ping/ping.py
gufo/ping/proto.py
gufo/ping/py.typed
gufo/ping/socket.py
gufo_ping.libs/libgcc_s-0cd532bd.so.1
gufo_ping-0.7.0.dist-info/METADATA
gufo_ping-0.7.0.dist-info/WHEEL
gufo_ping-0.7.0.dist-info/entry_points.txt
gufo_ping-0.7.0.dist-info/top_level.txt
gufo_ping-0.7.0.dist-info/RECORD
gufo_ping-0.7.0.dist-info/licenses/LICENSE.md
gufo_ping-0.7.0.dist-info/sboms/auditwheel.cdx.json
