Metadata-Version: 2.4
Name: gufo_ping
Version: 0.7.0
Summary: Gufo Ping is the accelerated Python asyncio IPv4/IPv6 ping implementation
Author: Gufo Labs
License-Expression: BSD-3-Clause
Project-URL: Bug Tracker, https://github.com/gufolabs/gufo_ping/issues
Project-URL: Changelog, https://github.com/gufolabs/gufo_ping/blob/master/CHANGELOG.md
Project-URL: Documentation, https://docs.gufolabs.com/gufo_ping/
Project-URL: Homepage, https://github.com/gufolabs/gufo_ping/
Project-URL: Source Code, https://github.com/gufolabs/gufo_ping/
Keywords: error
Classifier: Development Status :: 5 - Production/Stable
Classifier: Intended Audience :: Developers
Classifier: Intended Audience :: System Administrators
Classifier: Intended Audience :: Telecommunications Industry
Classifier: Programming Language :: Rust
Classifier: Programming Language :: Python :: 3.10
Classifier: Programming Language :: Python :: 3.11
Classifier: Programming Language :: Python :: 3.12
Classifier: Programming Language :: Python :: 3.13
Classifier: Programming Language :: Python :: 3.14
Classifier: Topic :: Software Development
Classifier: Topic :: Software Development :: Libraries
Classifier: Topic :: Software Development :: Libraries :: Python Modules
Classifier: Topic :: System :: Networking
Classifier: Topic :: System :: Networking :: Monitoring
Classifier: Operating System :: POSIX :: Linux
Classifier: Typing :: Typed
Requires-Python: >=3.10
License-File: LICENSE.md
Provides-Extra: build
Requires-Dist: setuptools-rust==1.5.2; extra == "build"
Provides-Extra: docs
Requires-Dist: mkdocs-gen-files==0.5.0; extra == "docs"
Requires-Dist: mkdocs-literate-nav==0.6.2; extra == "docs"
Requires-Dist: mkdocs-material==9.6.11; extra == "docs"
Requires-Dist: mkdocs-section-index==0.3.10; extra == "docs"
Requires-Dist: mkdocstrings[python]==0.29.1; extra == "docs"
Provides-Extra: ipython
Requires-Dist: ipython==9.6.0; extra == "ipython"
Provides-Extra: lint
Requires-Dist: mypy==1.18.2; extra == "lint"
Requires-Dist: ruff==0.14.0; extra == "lint"
Requires-Dist: types-PyYAML==6.0.12.3; extra == "lint"
Provides-Extra: test
Requires-Dist: PyYAML>=6.0; extra == "test"
Requires-Dist: pytest-benchmark==5.1.0; extra == "test"
Requires-Dist: pytest-cov==7.0.0; extra == "test"
Requires-Dist: pytest==8.4.2; extra == "test"
Dynamic: license-file
